notebook_validator/__init__.py
notebook_validator/validator.py
notebook_validator/nlp/__init__.py
notebook_validator/nlp/prompt_handler.py
notebook_validator/parsers/__init__.py
notebook_validator/parsers/notebook_parser.py
notebook_validator/reporters/__init__.py
notebook_validator/reporters/report_generator.py
notebook_validator/rules/__init__.py
notebook_validator/rules/coding_standards.py
notebook_validator/rules/naming_rules.py
notebook_validator-0.1.0.dist-info/METADATA
notebook_validator-0.1.0.dist-info/WHEEL
notebook_validator-0.1.0.dist-info/top_level.txt
notebook_validator-0.1.0.dist-info/RECORD
